play_lichess/__init__.py
play_lichess/exceptions.py
play_lichess/match.py
play_lichess/option.py
play_lichess/types.py
play_lichess-1.1.1.dist-info/LICENSE
play_lichess-1.1.1.dist-info/METADATA
play_lichess-1.1.1.dist-info/WHEEL
play_lichess-1.1.1.dist-info/top_level.txt
play_lichess-1.1.1.dist-info/RECORD
