Metadata-Version: 2.1
Name: play-lichess
Version: 1.1.1
Summary: Module for creating match links on Lichess that players can join
Home-page: https://github.com/DenverCoder1/play-lichess
Author: Jonah Lawrence
Author-email: jonah@freshidea.com
License: UNKNOWN
Project-URL: Bug Tracker, https://github.com/DenverCoder1/play-lichess/issues
Platform: UNKNOWN
Classifier: Programming Language :: Python :: 3
Classifier: License :: OSI Approved :: MIT License
Classifier: Operating System :: OS Independent
Classifier: Intended Audience :: Developers
Classifier: Topic :: Utilities
Requires-Python: >=3.8
Requires-Dist: aiohttp (<4,>=3.8)
